[
  {
    "tensach": "Nhà Giả Kim",
    "dongia": 150000,
    "soquyen": 5,
    "chomuon": true,
    "namxuatban": "1988-04-01T00:00:00.000Z",
    "image": "https://example.com/images/nha_gia_kim.jpg",
    "manxb": "63f2b1f6e8290b362afc4a1f",
    "tacgia": "Paulo Coelho",
    "khoa": false,
    "gioithieu": "Một cuốn tiểu thuyết huyền bí về hành trình của Santiago.",
    "theloai": ["Tiểu thuyết", "Huyền bí"]
  },
  {
    "tensach": "Đắc Nhân Tâm",
    "dongia": 120000,
    "soquyen": 3,
    "chomuon": true,
    "namxuatban": "1936-10-01T00:00:00.000Z",
    "image": "https://example.com/images/dac_nhan_tam.jpg",
    "manxb": "63f2b1f6e8290b362afc4a2f",
    "tacgia": "Dale Carnegie",
    "khoa": false,
    "gioithieu": "Cuốn sách hướng dẫn cách giao tiếp và ứng xử với mọi người.",
    "theloai": ["Phát triển bản thân"]
  },
  {
    "tensach": "Sapiens: Lược Sử Loài Người",
    "dongia": 200000,
    "soquyen": 8,
    "chomuon": true,
    "namxuatban": "2011-01-01T00:00:00.000Z",
    "image": "https://example.com/images/sapiens.jpg",
    "manxb": "63f2b1f6e8290b362afc4a3f",
    "tacgia": "Yuval Noah Harari",
    "khoa": false,
    "gioithieu": "Khám phá hành trình của loài người từ thời kỳ tiền sử đến hiện đại.",
    "theloai": ["Lịch sử", "Khoa học"]
  },
  {
    "tensach": "Tâm Lý Học Đám Đông",
    "dongia": 180000,
    "soquyen": 6,
    "chomuon": true,
    "namxuatban": "1895-01-01T00:00:00.000Z",
    "image": "https://example.com/images/tam_ly_hoc_dam_dong.jpg",
    "manxb": "63f2b1f6e8290b362afc4a4f",
    "tacgia": "Gustave Le Bon",
    "khoa": false,
    "gioithieu": "Nghiên cứu về hành vi của đám đông và ảnh hưởng của nó đến quyết định.",
    "theloai": ["Tâm lý học"]
  },
  {
    "tensach": "Người Giữ Thời Gian",
    "dongia": 220000,
    "soquyen": 4,
    "chomuon": true,
    "namxuatban": "2020-05-01T00:00:00.000Z",
    "image": "https://example.com/images/nguoi_giu_thoi_gian.jpg",
    "manxb": "63f2b1f6e8290b362afc4a5f",
    "tacgia": "Khaled Hosseini",
    "khoa": false,
    "gioithieu": "Cuốn tiểu thuyết cảm động về tình bạn và những cuộc chiến tranh.",
    "theloai": ["Tiểu thuyết", "Tình bạn"]
  },
  {
    "tensach": "Chạy Đi! Đừng Dừng Lại",
    "dongia": 170000,
    "soquyen": 2,
    "chomuon": true,
    "namxuatban": "2019-07-01T00:00:00.000Z",
    "image": "https://example.com/images/chay_di.jpg",
    "manxb": "63f2b1f6e8290b362afc4a6f",
    "tacgia": "Khaled Hosseini",
    "khoa": false,
    "gioithieu": "Một cuốn sách truyền cảm hứng về sự kiên trì.",
    "theloai": ["Phát triển bản thân"]
  },
  {
    "tensach": "Khi Hơi Thở Hóa Thinh Không",
    "dongia": 210000,
    "soquyen": 7,
    "chomuon": true,
    "namxuatban": "2015-01-01T00:00:00.000Z",
    "image": "https://example.com/images/khi_hoi_tho.jpg",
    "manxb": "63f2b1f6e8290b362afc4a7f",
    "tacgia": "Paul Kalanithi",
    "khoa": false,
    "gioithieu": "Cuốn hồi ký sâu sắc về cuộc sống và cái chết.",
    "theloai": ["Hồi ký"]
  },
  {
    "tensach": "Hành Trình Về Phương Đông",
    "dongia": 190000,
    "soquyen": 9,
    "chomuon": true,
    "namxuatban": "1970-01-01T00:00:00.000Z",
    "image": "https://example.com/images/hanh_trinh_ve_phuong_dong.jpg",
    "manxb": "63f2b1f6e8290b362afc4a8f",
    "tacgia": "Nguyễn Bính",
    "khoa": false,
    "gioithieu": "Một cuốn sách về hành trình khám phá văn hóa phương Đông.",
    "theloai": ["Văn học"]
  },
  {
    "tensach": "Cách Mạng Một Cú",
    "dongia": 160000,
    "soquyen": 1,
    "chomuon": true,
    "namxuatban": "2018-03-01T00:00:00.000Z",
    "image": "https://example.com/images/cach_mang_mot_cu.jpg",
    "manxb": "63f2b1f6e8290b362afc4a9f",
    "tacgia": "Malcolm Gladwell",
    "khoa": false,
    "gioithieu": "Phân tích về các thay đổi lớn trong xã hội.",
    "theloai": ["Khoa học"]
  },
  {
    "tensach": "Cô Gái Đến Từ Hôm Qua",
    "dongia": 130000,
    "soquyen": 10,
    "chomuon": true,
    "namxuatban": "2016-04-01T00:00:00.000Z",
    "image": "https://example.com/images/co_gai_den_tu_hom_qua.jpg",
    "manxb": "63f2b1f6e8290b362afc4a0f",
    "tacgia": "Nguyễn Nhật Ánh",
    "khoa": false,
    "gioithieu": "Một cuốn tiểu thuyết tuổi teen ngọt ngào.",
    "theloai": ["Tiểu thuyết", "Văn học"]
  }
]
